compas_slicer/__init__.py
compas_slicer/__main__.py
compas_slicer/geometry/__init__.py
compas_slicer/geometry/layer.py
compas_slicer/geometry/path.py
compas_slicer/geometry/print_point.py
compas_slicer/parameters/__init__.py
compas_slicer/parameters/defaults_gcode.py
compas_slicer/parameters/defaults_interpolation_slicing.py
compas_slicer/parameters/defaults_layers.py
compas_slicer/parameters/defaults_print_organization.py
compas_slicer/parameters/get_param.py
compas_slicer/post_processing/__init__.py
compas_slicer/post_processing/generate_brim.py
compas_slicer/post_processing/generate_raft.py
compas_slicer/post_processing/reorder_vertical_layers.py
compas_slicer/post_processing/seams_align.py
compas_slicer/post_processing/seams_smooth.py
compas_slicer/post_processing/simplify_paths_rdp.py
compas_slicer/post_processing/sort_into_vertical_layers.py
compas_slicer/post_processing/sort_paths_minimum_travel_time.py
compas_slicer/post_processing/spiralize_contours.py
compas_slicer/post_processing/unify_paths_orientation.py
compas_slicer/post_processing/zig_zag_open_paths.py
compas_slicer/pre_processing/__init__.py
compas_slicer/pre_processing/gradient_evaluation.py
compas_slicer/pre_processing/interpolation_slicing_preprocessor.py
compas_slicer/pre_processing/positioning.py
compas_slicer/pre_processing/preprocessing_utils/__init__.py
compas_slicer/pre_processing/preprocessing_utils/assign_vertex_distance.py
compas_slicer/pre_processing/preprocessing_utils/compound_target.py
compas_slicer/pre_processing/preprocessing_utils/geodesics.py
compas_slicer/pre_processing/preprocessing_utils/gradient.py
compas_slicer/pre_processing/preprocessing_utils/mesh_attributes_handling.py
compas_slicer/pre_processing/preprocessing_utils/region_split.py
compas_slicer/pre_processing/preprocessing_utils/topological_sorting.py
compas_slicer/print_organization/__init__.py
compas_slicer/print_organization/base_print_organizer.py
compas_slicer/print_organization/interpolation_print_organizer.py
compas_slicer-0.7.0.dist-info/LICENSE
compas_slicer-0.7.0.dist-info/METADATA
compas_slicer-0.7.0.dist-info/WHEEL
compas_slicer-0.7.0.dist-info/top_level.txt
compas_slicer-0.7.0.dist-info/RECORD
