Metadata-Version: 2.1
Name: compas_slicer
Version: 0.7.0
Summary: Slicing package for FDM 3D Printing with COMPAS
Home-page: https://github.com/compas-dev/compas_slicer
Author: Ioanna Mitropoulou and Joris Burger
Author-email: mitropoulou@arch.ethz.ch
License: MIT license
Classifier: Development Status :: 4 - Beta
Classifier: Intended Audience :: Developers
Classifier: Topic :: Scientific/Engineering
Classifier: License :: OSI Approved :: MIT License
Classifier: Operating System :: Unix
Classifier: Operating System :: POSIX
Classifier: Operating System :: Microsoft :: Windows
Classifier: Programming Language :: Python :: 3.8
Classifier: Programming Language :: Python :: 3.9
Classifier: Programming Language :: Python :: Implementation :: CPython
Classifier: Programming Language :: Python :: Implementation :: IronPython
Requires-Python: >=3.8
License-File: LICENSE
Requires-Dist: attrs >=19.2.0
Requires-Dist: compas <2.0.0,>=1.16.0
Requires-Dist: networkx <3.2,>=2.5
Requires-Dist: numpy <=1.23.2
Requires-Dist: progressbar2 <4.4,>=3.53
Requires-Dist: pyclipper <1.3.0,>=1.2.0
Requires-Dist: rdp ==0.8
Requires-Dist: libigl <2.5.0,>=2.4.1
